gempaterkini/__init__.py
gempaterkini/gempaUPDATE/__init__.py
update_gempa_indonesia-0.0.5.dist-info/LICENSE
update_gempa_indonesia-0.0.5.dist-info/METADATA
update_gempa_indonesia-0.0.5.dist-info/WHEEL
update_gempa_indonesia-0.0.5.dist-info/top_level.txt
update_gempa_indonesia-0.0.5.dist-info/RECORD
